<?xml version="1.0" encoding="UTF-8"?><JPS xmlns:xsi="http://www.w3.org/2001/XMLSchema-instance" xsi:noNamespaceSchemaLocation="JPS" AN="1959" CODE="JPJ" MOIS="07"><DEBUA N="1"></DEBUA><DECI><TDECI></TDECI><DEBUR DATE="10/07/1959" N="1"></DEBUR><INFO COLLA="OUI" ID="IJPS-112340605"><NINFO>1</NINFO><REFDOC DATE="10/07/1959" ID="RC0JPS5907-10961576" JURI-DATE="1959-07-10" JURI-JURISDICTION="Cour de cassation" JURI-JURISDICTION-REFID="CASS" JURI-NUMBER="3221" NATURE="Cass. soc." NOM="Bessac c/ Vigroux" RC="3221"> Cass. soc. 10 juillet 1959 n° 3221 Bessac c/ Vigroux </REFDOC><ABS><DESC></DESC></ABS><TXD><AL>Sur le moyen unique, pris de la violation des articles 4 et 5 de la loi du 21 octobre 1946, 23, Livre I<E>er</E> du Code du travail, 54 k, Livre II du même Code et 7 de la loi du 20 avril 1810 pour défaut de motifs, manque de base légale et défaut de réponse aux conclusions ;</AL><AL>Attendu que Vigroux, au service de l'entreprise des travaux publics Bessac, ayant été congédié le 23 décembre 1952, a assigné son employeur en payement de différentes sommes à titre d'indemnités d'intempéries, de préavis, de congés payés et à titre de salaires non versés ; que le conseil des prud'hommes a fait droit à tous ces chefs de demandes ;</AL><AL>Sur la première branche du moyen :</AL><AL>Attendu que Bessac fait grief à la décision attaquée d'avoir alloué une indemnité correspondant à deux journées d'intempéries alors que d'une part le conseil des prud'hommes, méconnaissant les dispositions de l'article 4 de la loi du 21 octobre 1946, a compté le délai de référence à partir de la date d'entrée de l'intéressé au service de l'entreprise et que d'autre part, en tout état de cause une seule journée pouvait donner lieu à indemnité, l'autre ayant été récupérée ;</AL><AL>Mais attendu d'abord qu'après avoir justement rappelé que pour bénéficier de l'indemnité d'intempéries, le salarié doit avoir accompli deux cents heures de travail au moins au cours des deux mois qui précèdent l'arrêt du travail, la sentence critiquée relève par une constatation de fait qui échappe au contrôle de la Cour de cassation, que l'ouvrier justifiait de plus de deux cents heures de présence au moment de l'arrêt du travail ;</AL><AL>Et attendu qu'aux termes de l'article 4 du décret d'application du 11 décembre 1946, les heures de travail effectuées en remplacement des heures perdues pour cause d'intempéries sont rémunérées sans qu'il y ait à tenir compte du fait qu'elles ont donné lieu à indemnisation laquelle est en définitive à la charge de la caisse et non de l'employeur ; que n'étant pas contesté que le travail avait dû être interrompu par suite du mauvais temps les 17 et 18 décembre 1952, c'est à bon droit que le conseil a alloué une indemnité correspondant au chômage forcé de ces deux journées, sans s'arrêter au fait que l'une de ces journées avait, entre-temps, été récupérée ; qu'ainsi le moyen n'est pas fondé en sa première branche ;</AL><AL>Sur la deuxième branche :</AL><AL>Attendu que Bessac reproche encore au conseil des prud'hommes d'avoir alloué une indemnité de préavis de huit jours sans justifier d'un usage se rapportant à ce délai, tout en passant sous silence des faits graves établissant la volonté délibérée de l'ouvrier de se soustraire à ses propres obligations et en attribuant à la demande de licenciement adressée à l'Inspection du travail une portée et un sens qu'elle n'a pas ;</AL><AL>Mais attendu qu'examinant chacun des griefs qui, aux dires de Bessac, justifiaient le brusque congédiement de son ouvrier, le conseil des prud'hommes observe que le reproche fait au salarié de s'être absenté du chantier une journée ne justifiait pas son renvoi sans préavis, que les parties sont en désaccord relativement à un prétendu refus de travail suivi d'un abandon de chantier dont Bessac ne rapporte pas la preuve ;</AL><AL>Attendu qu'en l'état de ces énonciations et abstraction faite de tout autre motif qui peut être tenu pour surabondant, les juges du fait étaient fondés à décider que Bessac n'était pas dispensé de l'obligation d'observer le délai de préavis et l'ont à juste titre condamné à payer de ce chef une indemnité égale au délai de préavis conforme aux usages locaux dont il est formellement constaté l'existence et la durée ;</AL><AL>D'où il suit que le grief ne saurait être retenu ;</AL><AL>Sur la troisième branche :</AL><AL>Attendu que le demandeur fait également grief au conseil des prud'hommes de l'avoir personnellement condamné au payement de l'indemnité de congés payés alors qu'étant affilié à une caisse de congés payés, il ne pouvait être tenu que de délivrer à son ouvrier une attestation de ses droits à ce congé, attestation qu'il offrait de donner ;</AL><AL>Mais attendu que constatant qu'en dépit de ses affirmations, Bessac n'apporte pas la preuve qu'il est régulièrement affilié à la caisse de congés payés et qu'il n'a pas remis à son ouvrier la pièce justificative lui permettant de conserver ses droits, le conseil des prud'hommes, a, à bon droit, décidé que le salarié ne pouvant attendre la régularisation de cette situation et ne devant pas être victime de la négligence de son ancien patron, celui-ci devait être condamné à lui verser l'indemnité à laquelle il ne pouvait prétendre de ce chef ;</AL><AL>Qu'ainsi le grief n'est pas fondé ;</AL><AL>Mais sur la quatrième branche du moyen unique :</AL><AL>Vu l'article 7 de la loi du 20 avril 1810 ;</AL><AL>Attendu que les jugements doivent être motivés que, l'insuffisance des motifs équivaut à leur absence ;</AL><AL>Or attendu qu'après s'être borné à énoncer que les parties étaient d'accord sur la question des salaires restant dus, le conseil des prud'hommes a condamné l'employeur à payer de ce chef à Vigroux la somme de 1 500 F qu'il réclamait, sans répondre aux conclusions de Bessac faisant valoir que s'il devait encore 1 775 F de salaires, il y avait lieu de déduire de cette somme un acompte de 1 000 F antérieurement versé à l'ouvrier ;</AL><AL>Qu'en statuant ainsi, le conseil des prud'hommes n'a pas justifié légalement sa décision ;</AL><AL>Par ces motifs :</AL><AL>Casse et annule mais seulement du chef de la condamnation prononcée au sujet des salaires restant dus, le jugement rendu le 13 mars 1953 par le conseil des prud'hommes d'Agen, et renvoie devant le conseil des prud'hommes de Cahors.</AL></TXD></INFO><FINUR></FINUR><FINUA></FINUA><DEBUA N="2"></DEBUA><DEBUR DATE="10/07/1959" N="2"></DEBUR><INFO COLLA="OUI" ID="IJPS5907-1137654"><NINFO>2</NINFO><REFDOC DATE="10/07/1959" ID="RC0JPS5907-10961577" JURI-DATE="1959-07-10" JURI-JURISDICTION="Cour de cassation" JURI-JURISDICTION-REFID="CASS" JURI-NUMBER="58-40 047" NATURE="Cass. soc." NOM="Sté pharmaceutique des établissements Gayral c/ Dahan" REF="58-40 047">Cass. soc. 10 juillet 1959 n° 58-40.047 Sté pharmaceutique des établissements Gayral c/ Dahan</REFDOC><ABS><DESC></DESC></ABS><TXD><AL>Sur les trois moyens réunis :</AL><AL>Vu les articles 1134 du Code civil et 7 de la loi du 20 avril 1810 ;</AL><AL>Attendu qu'aux termes du premier de ces textes, les conventions légalement formées tiennent lieu de loi à ceux qui les ont faites ;</AL><AL>Attendu que Dahan, engagé en 1955 au service de la Société pharmaceutique des anciens établissements Gayral en qualité de « visiteur médical » au salaire mensuel de 60 000 F pour une période d'essai de trois mois, avait pour mission de présenter aux médecins des départements d'Algérie des produits pharmaceutiques dans le but d'en provoquer ou d'en intensifier la prescription, en leur exposant les propriétés thérapeutiques des spécialités pharmaceutiques présentées et d'en faire ressortir les avantages et les indications ;</AL><AL>Que, son activité se trouvant des plus restreintes par suite des événements d'Algérie, la société lui proposa, à l'expiration de la période d'essai, de renouveler cette période pour trois mois, soit jusqu'au 31 décembre 1955 ; que Dahan accepta cette proposition, mais que les circonstances ne lui permettant toujours pas les déplacements envisagés, la société décida de se séparer de lui à l'expiration de la seconde période d'essai et lui versa ses appointements du mois de décembre ;</AL><AL>Or, attendu que le jugement attaqué pour accorder à Dahan, outre une indemnité de congé payé, l'indemnité de préavis qu'il réclamait, a considéré, d'une part, que le statut professionnel des représentants de commerce s'appliquait aux visiteurs médicaux et, d'autre part, que l'article 29 L du livre 1<E>er</E> du Code du travail limitant à trois mois la durée maxima d'engagement à l'essai des représentants de commerce, la seconde période d'essai convenue entre les parties, constituait un nouveau contrat « à durée indéterminée » ;</AL><AL>Mais attendu qu'aux termes des articles 1<E>er</E> et suivants de l'annexe à la convention collective nationale de l'industrie pharmaceutique, intervenue le 6 avril 1956 et étendue par l'arrêté du 15 novembre 1956, il est formellement précisé et reconnu que les dispositions de la loi du 18 juillet 1937 (articles 29 K et suivants du livre 1<E>er</E> du Code du travail) ne sont pas applicables aux visiteurs médicaux, étant entendu que toute activité commerciale et, en particulier, la prise de commandes, leur est formellement interdite ;</AL><AL>Attendu que, dès lors qu'il n'était pas contesté en l'espèce que Dahan ne se livrait à aucune activité de nature commerciale pour le compte de la Société pharmaceutique des anciens établissements Gayral, mais qu'il était un visiteur médical au sens de la convention susvisée, c'est-à-dire un employé salarié des services commerciaux, il se trouvait ainsi exclu du statut des représentants de commerce ;</AL><AL>Attendu, d'autre part, que l'article 23 du livre 1<E>er</E> du Code du travail ne contient aucune disposition impérative prescrivant une seule période d'essai ne pouvant excéder trois mois ; que le nouveau contrat, dont il n'a pas été allégué qu'il avait été conclu pour faire échec aux droits de l'employé, avait le même caractère de contrat à l'essai que le contrat initial, les parties étant demeurées libres de déterminer entre elles la durée de la nouvelle période d'essai et l'ayant fixée à trois mois ; qu'un tel contrat ne comporte pas de délai-congé ;</AL><AL>D'où il suit qu'en attribuant à Dahan le statut de représentant de commerce et en condamnant la Société pharmaceutique des anciens établissements Gayral à lui payer une indemnité de préavis, alors qu'il avait cessé normalement ses fonctions à l'expiration de la période d'essai convenue entre les parties, les juges du fond ont violé le texte susvisé et n'ont pas donné de base légale à leur décision ;</AL><AL>Par ces motifs :</AL><AL>Casse et annule, mais seulement en ce qui concerne l'indemnité de préavis, le jugement rendu le 20 juin 1957 par le tribunal civil d'Alger, et renvoie devant le tribunal de grande instance d'Oran.</AL></TXD></INFO><FINUR></FINUR></DECI><FINUA></FINUA></JPS>