<?xml version="1.0" encoding="UTF-8"?><JPS xmlns:xsi="http://www.w3.org/2001/XMLSchema-instance" xsi:noNamespaceSchemaLocation="JPS" AN="1931" CODE="JPJ" MOIS="12"><DEBUA N="1"></DEBUA><DECI><TDECI></TDECI><DEBUR DATE="04/12/1931" N="1"></DEBUR><INFO COLLA="OUI" ID="IJPS-111531465"><NINFO>1</NINFO><REFDOC DATE="04/12/1931" ID="RC0JPS3112-1096472" JURI-DATE="1931-12-04" JURI-JURISDICTION="Conseil d'État" JURI-JURISDICTION-REFID="CE" JURI-NUMBER="78780" NATURE="CE" NOM="Sieur X c/" REF="78780">CE n°78780 4 décembre 1931 Sieur X c/…</REFDOC><ABS><DESC></DESC></ABS><TXD><AL>Considérant qu'en vertu du contrat passé par lui avec la maison N…, le sieur X… pouvait recevoir, en sus de ses appointements, une somme portée à son crédit à un compte spécial ouvert sur les livres de la Société, et dont le montant ne devenait exigible que cinq ans après sa sortie de l'établissement et à la condition expresse de ne manquer à aucun des engagements du contrat ;</AL><AL>Considérant qu'il résulte de ce qui précède que les sommes figurant à ce compte n'étant pas exigibles par le sieur X… n'étaient pas à sa disposition, au sens des lois des 15 juillet 1914 et 31 juillet 1917 ; qu'ainsi, il y a lieu de déduire, tant pour le calcul de l'impôt sur les salaires que pour celui de l'impôt général du sieur X…, pour 1919, en sus de la somme de 20 000 F déjà admise par le Conseil de préfecture, une somme de 4 827,50 F, portée au compte spécial.</AL></TXD></INFO><FINUR></FINUR></DECI><FINUA></FINUA></JPS>